djg.py
djg-0.1.1.dist-info/METADATA
djg-0.1.1.dist-info/WHEEL
djg-0.1.1.dist-info/licenses/LICENSE
djg-0.1.1.dist-info/RECORD
