Metadata-Version: 2.3
Name: djg
Version: 0.1.1
Summary: JSON generation based on schema.
Project-URL: Repository, https://github.com/Domerpig/djg
Project-URL: Issues, https://github.com/Domerpig/djg/issues
Author-email: Domink Moos <dominik.moos@proton.me>
License: MIT License
License-File: LICENSE
Keywords: json,json-generation,json-schema
Classifier: Development Status :: 3 - Alpha
Classifier: License :: OSI Approved :: MIT License
Classifier: Programming Language :: Python :: 3
Classifier: Programming Language :: Python :: 3.10
Classifier: Programming Language :: Python :: 3.11
Classifier: Programming Language :: Python :: 3.12
Classifier: Topic :: Utilities
Requires-Python: >=3.10
Requires-Dist: exrex
